temu_api/__init__.py
temu_api/__version__.py
temu_api/api/__init__.py
temu_api/api/ads.py
temu_api/api/aftersales.py
temu_api/api/auth.py
temu_api/api/base.py
temu_api/api/fulfillment.py
temu_api/api/logistics.py
temu_api/api/order.py
temu_api/api/price.py
temu_api/api/product.py
temu_api/api/promotion.py
temu_api/utils/api_response.py
temu_api/utils/base_client.py
temu_api/utils/helpers.py
temu_api-0.2.1.dist-info/LICENSE
temu_api-0.2.1.dist-info/METADATA
temu_api-0.2.1.dist-info/WHEEL
temu_api-0.2.1.dist-info/top_level.txt
temu_api-0.2.1.dist-info/RECORD
