Metadata-Version: 2.1
Name: temu_api
Version: 0.2.1
Summary: temu 开发者sdk temu api
Author-email: XIE7654 <765462425@qq.com>
License: MIT License
Project-URL: Homepage, https://github.com/XIE7654/temu_api
Project-URL: Repository, https://github.com/XIE7654/temu_api
Classifier: Programming Language :: Python :: 3
Classifier: License :: OSI Approved :: MIT License
Classifier: Operating System :: OS Independent
Requires-Python: >=3.7
License-File: LICENSE
Requires-Dist: requests >=2.0
